{
"bones": [
	{ "name": "root" },
	{ "name": "human0", "parent": "root", "x": 500, "y": -15 },
	{ "name": "human1", "parent": "root", "x": 500, "y": -15 },
	{ "name": "human2", "parent": "root", "x": 500, "y": -15 },
	{ "name": "human3", "parent": "root", "x": 500, "y": -15 },
	{ "name": "human4", "parent": "root", "x": 500, "y": -15 },
	{ "name": "station", "parent": "root" }
],
"slots": [
	{ "name": "abandonedstation", "bone": "station", "attachment": "flightScene/eyecandy/abandonedstation" },
	{ "name": "human0", "bone": "human0" },
	{ "name": "human1", "bone": "human1" },
	{ "name": "human2", "bone": "human2" },
	{ "name": "human3", "bone": "human3" },
	{ "name": "human4", "bone": "human4" },
	{ "name": "cargo0", "bone": "human0" },
	{ "name": "cargo1", "bone": "human1" },
	{ "name": "cargo2", "bone": "human2" },
	{ "name": "cargo3", "bone": "human3" },
	{ "name": "cargo4", "bone": "human4" }
],
"skins": [{
	"name":"default",
	"attachments": {
		"abandonedstation": {
			"flightScene/eyecandy/abandonedstation": { "width": 639, "height": 435 }
		},
		"cargo0": {
			"flightScene/cargoBlue": { "scaleX": 0.5, "scaleY": 0.5, "width": 50, "height": 50 },
			"flightScene/cargoGreen": { "scaleX": 0.5, "scaleY": 0.5, "width": 50, "height": 50 },
			"flightScene/cargoRed": { "scaleX": 0.5, "scaleY": 0.5, "width": 50, "height": 50 },
			"flightScene/cargoYellow": { "scaleX": 0.5, "scaleY": 0.5, "width": 50, "height": 50 }
		},
		"cargo1": {
			"flightScene/cargoBlue": { "scaleX": 0.5, "scaleY": 0.5, "width": 50, "height": 50 },
			"flightScene/cargoGreen": { "scaleX": 0.5, "scaleY": 0.5, "width": 50, "height": 50 },
			"flightScene/cargoRed": { "scaleX": 0.5, "scaleY": 0.5, "width": 50, "height": 50 },
			"flightScene/cargoYellow": { "scaleX": 0.5, "scaleY": 0.5, "width": 50, "height": 50 }
		},
		"cargo2": {
			"flightScene/cargoBlue": { "scaleX": 0.5, "scaleY": 0.5, "width": 50, "height": 50 },
			"flightScene/cargoGreen": { "scaleX": 0.5, "scaleY": 0.5, "width": 50, "height": 50 },
			"flightScene/cargoRed": { "scaleX": 0.5, "scaleY": 0.5, "width": 50, "height": 50 },
			"flightScene/cargoYellow": { "scaleX": 0.5, "scaleY": 0.5, "width": 50, "height": 50 }
		},
		"cargo3": {
			"flightScene/cargoBlue": { "scaleX": 0.5, "scaleY": 0.5, "width": 50, "height": 50 },
			"flightScene/cargoGreen": { "scaleX": 0.5, "scaleY": 0.5, "width": 50, "height": 50 },
			"flightScene/cargoRed": { "scaleX": 0.5, "scaleY": 0.5, "width": 50, "height": 50 },
			"flightScene/cargoYellow": { "scaleX": 0.5, "scaleY": 0.5, "width": 50, "height": 50 }
		},
		"cargo4": {
			"flightScene/cargoBlue": { "scaleX": 0.5, "scaleY": 0.5, "width": 50, "height": 50 },
			"flightScene/cargoGreen": { "scaleX": 0.5, "scaleY": 0.5, "width": 50, "height": 50 },
			"flightScene/cargoRed": { "scaleX": 0.5, "scaleY": 0.5, "width": 50, "height": 50 },
			"flightScene/cargoYellow": { "scaleX": 0.5, "scaleY": 0.5, "width": 50, "height": 50 }
		},
		"human0": {
			"flightScene/alienCyan": { "y": 15, "width": 50, "height": 50 },
			"flightScene/alienOrange": { "y": 15, "width": 50, "height": 50 },
			"flightScene/alienPurple": { "y": 15, "width": 50, "height": 50 },
			"flightScene/human": { "y": 14.99, "width": 50, "height": 50 }
		},
		"human1": {
			"flightScene/alienCyan": { "y": 15, "width": 50, "height": 50 },
			"flightScene/alienOrange": { "y": 15, "width": 50, "height": 50 },
			"flightScene/alienPurple": { "y": 15, "width": 50, "height": 50 },
			"flightScene/human": { "y": 14.99, "width": 50, "height": 50 }
		},
		"human2": {
			"flightScene/alienCyan": { "y": 15, "width": 50, "height": 50 },
			"flightScene/alienOrange": { "y": 15, "width": 50, "height": 50 },
			"flightScene/alienPurple": { "y": 15, "width": 50, "height": 50 },
			"flightScene/human": { "y": 14.99, "width": 50, "height": 50 }
		},
		"human3": {
			"flightScene/alienCyan": { "y": 15, "width": 50, "height": 50 },
			"flightScene/alienOrange": { "y": 15, "width": 50, "height": 50 },
			"flightScene/alienPurple": { "y": 15, "width": 50, "height": 50 },
			"flightScene/human": { "y": 15, "width": 50, "height": 50 }
		},
		"human4": {
			"flightScene/alienCyan": { "y": 15, "width": 50, "height": 50 },
			"flightScene/alienOrange": { "y": 15, "width": 50, "height": 50 },
			"flightScene/alienPurple": { "y": 15, "width": 50, "height": 50 },
			"flightScene/human": { "y": 14.99, "width": 50, "height": 50 }
		}
	}
}],
"animations": {
	"loot": {
		"bones": {
			"human0": {
				"translate": [
					{
						"time": 0,
						"x": 0,
						"y": 0,
						"curve": [ 0.25, 0, 0.117, 0.99 ]
					},
					{ "time": 1.6666, "x": -317.67, "y": 81.31 },
					{ "time": 1.8666, "x": -364.79, "y": 53.95, "curve": "stepped" },
					{ "time": 2.6666, "x": -364.79, "y": 53.95 },
					{
						"time": 2.8666,
						"x": -323.75,
						"y": 60.79,
						"curve": [ 0.25, 0, 0.071, 1 ]
					},
					{ "time": 4.3333, "x": 0, "y": 15 }
				],
				"scale": [
					{
						"time": 0,
						"x": 0.1,
						"y": 0.1,
						"curve": [ 0.218, 0.99, 0.75, 1 ]
					},
					{ "time": 1.6666, "x": 1, "y": 1, "curve": "stepped" },
					{
						"time": 2.8666,
						"x": 1,
						"y": 1,
						"curve": [ 0.25, 0, 1, 0.41 ]
					},
					{ "time": 4.3333, "x": 0.1, "y": 0.1 }
				]
			},
			"station": {
				"translate": [
					{ "time": 1.8666, "x": 0, "y": 0 },
					{ "time": 1.9, "x": 22.8, "y": 27.4 },
					{ "time": 1.9333, "x": 0.8, "y": -3.8 },
					{ "time": 1.9666, "x": 10.6, "y": -3 },
					{ "time": 2, "x": -9.1, "y": 16 },
					{ "time": 2.0333, "x": -3, "y": 9.89 },
					{ "time": 2.0666, "x": -11.4, "y": -3 },
					{ "time": 2.1, "x": 1.5, "y": 0.8 },
					{ "time": 2.1333, "x": -6.1, "y": 14.4 },
					{ "time": 2.1666, "x": 0, "y": 15.2 },
					{ "time": 2.2, "x": 3, "y": -4.6 },
					{ "time": 2.2333, "x": 1.5, "y": 9.1 },
					{ "time": 2.2666, "x": 17.5, "y": 0 },
					{ "time": 2.3, "x": 0, "y": 0 }
				]
			},
			"human1": {
				"translate": [
					{
						"time": 0,
						"x": 0,
						"y": 5,
						"curve": [ 0.25, 0, 0.431, 0.99 ]
					},
					{ "time": 1.6666, "x": -349, "y": 115 },
					{ "time": 1.8666, "x": -404, "y": 74, "curve": "stepped" },
					{ "time": 2.6666, "x": -404, "y": 74 },
					{
						"time": 2.8666,
						"x": -371,
						"y": 118,
						"curve": [ 0.25, 0, 0.206, 1 ]
					},
					{ "time": 4.3333, "x": 0, "y": 15 }
				],
				"scale": [
					{
						"time": 0,
						"x": 0.1,
						"y": 0.1,
						"curve": [ 0.218, 0.99, 0.75, 1 ]
					},
					{ "time": 1.6666, "x": 1, "y": 1, "curve": "stepped" },
					{
						"time": 2.8666,
						"x": 1,
						"y": 1,
						"curve": [ 0.25, 0, 1, 0.41 ]
					},
					{ "time": 4.3333, "x": 0.1, "y": 0.1 }
				]
			},
			"human2": {
				"translate": [
					{
						"time": 0,
						"x": 0,
						"y": 10,
						"curve": [ 0.25, 0, 0.557, 0.99 ]
					},
					{ "time": 1.6666, "x": -351, "y": 47 },
					{ "time": 1.8666, "x": -418, "y": 33, "curve": "stepped" },
					{ "time": 2.6666, "x": -418, "y": 33 },
					{
						"time": 2.8666,
						"x": -361,
						"y": -5.99,
						"curve": [ 0.25, 0, 0.089, 0.99 ]
					},
					{ "time": 4.3333, "x": 0, "y": 10 }
				],
				"scale": [
					{
						"time": 0,
						"x": 0.1,
						"y": 0.1,
						"curve": [ 0.218, 0.99, 0.75, 1 ]
					},
					{ "time": 1.6666, "x": 1, "y": 1, "curve": "stepped" },
					{
						"time": 2.8666,
						"x": 1,
						"y": 1,
						"curve": [ 0.25, 0, 1, 0.41 ]
					},
					{ "time": 4.3333, "x": 0.1, "y": 0.1 }
				]
			},
			"human3": {
				"translate": [
					{
						"time": 0,
						"x": 0,
						"y": 15,
						"curve": [ 0.25, 0, 0.117, 0.99 ]
					},
					{ "time": 1.6666, "x": -375, "y": 149 },
					{ "time": 1.8666, "x": -431, "y": 84, "curve": "stepped" },
					{ "time": 2.6666, "x": -431, "y": 84 },
					{
						"time": 2.8666,
						"x": -361,
						"y": 63,
						"curve": [ 0.25, 0, 0.402, 1 ]
					},
					{ "time": 4.3333, "x": 0, "y": 15 }
				],
				"scale": [
					{
						"time": 0,
						"x": 0.1,
						"y": 0.1,
						"curve": [ 0.218, 0.99, 0.75, 1 ]
					},
					{ "time": 1.6666, "x": 1, "y": 1, "curve": "stepped" },
					{
						"time": 2.8666,
						"x": 1,
						"y": 1,
						"curve": [ 0.25, 0, 1, 0.41 ]
					},
					{ "time": 4.3333, "x": 0.1, "y": 0.1 }
				]
			},
			"human4": {
				"translate": [
					{
						"time": 0,
						"x": 0,
						"y": 20,
						"curve": [ 0.25, 0, 0.445, 1 ]
					},
					{ "time": 1.6666, "x": -376.99, "y": -16.99 },
					{ "time": 1.8666, "x": -448, "y": 30, "curve": "stepped" },
					{ "time": 2.6666, "x": -448, "y": 30 },
					{
						"time": 2.8666,
						"x": -390,
						"y": 16.99,
						"curve": [ 0.25, 0, 0.376, 0.99 ]
					},
					{ "time": 4.3333, "x": 0, "y": 20 }
				],
				"scale": [
					{
						"time": 0,
						"x": 0.1,
						"y": 0.1,
						"curve": [ 0.218, 0.99, 0.75, 1 ]
					},
					{ "time": 1.6666, "x": 1, "y": 1, "curve": "stepped" },
					{
						"time": 2.8666,
						"x": 1,
						"y": 1,
						"curve": [ 0.25, 0, 1, 0.41 ]
					},
					{ "time": 4.3333, "x": 0.1, "y": 0.1 }
				]
			}
		},
		"slots": {
			"cargo1": {
				"attachment": [
					{ "time": 0, "name": "flightScene/cargoBlue" }
				],
				"color": [
					{ "time": 0, "color": "ffffff00", "curve": "stepped" },
					{ "time": 2.6666, "color": "ffffff00" },
					{ "time": 2.8666, "color": "ffffffff", "curve": "stepped" },
					{ "time": 4.3333, "color": "ffffffff" },
					{ "time": 4.6666, "color": "ffffff00" }
				]
			},
			"cargo3": {
				"attachment": [
					{ "time": 0, "name": "flightScene/cargoBlue" }
				],
				"color": [
					{ "time": 0, "color": "ffffff00", "curve": "stepped" },
					{ "time": 2.6666, "color": "ffffff00" },
					{ "time": 2.8666, "color": "ffffffff", "curve": "stepped" },
					{ "time": 4.3333, "color": "ffffffff" },
					{ "time": 4.6666, "color": "ffffff00" }
				]
			},
			"human0": {
				"attachment": [
					{ "time": 0, "name": "flightScene/human" }
				],
				"color": [
					{ "time": 0, "color": "ffffff00" },
					{ "time": 0.3333, "color": "ffffffff", "curve": "stepped" },
					{ "time": 1.6666, "color": "ffffffff" },
					{ "time": 1.8666, "color": "ffffff00", "curve": "stepped" },
					{ "time": 2.6666, "color": "ffffff00" },
					{ "time": 2.8666, "color": "ffffffff", "curve": "stepped" },
					{ "time": 4.3333, "color": "ffffffff" },
					{ "time": 4.6666, "color": "ffffff00" }
				]
			},
			"human3": {
				"attachment": [
					{ "time": 0, "name": "flightScene/human" }
				],
				"color": [
					{ "time": 0, "color": "ffffff00" },
					{ "time": 0.3333, "color": "ffffffff", "curve": "stepped" },
					{ "time": 1.6666, "color": "ffffffff" },
					{ "time": 1.8666, "color": "ffffff00", "curve": "stepped" },
					{ "time": 2.6666, "color": "ffffff00" },
					{ "time": 2.8666, "color": "ffffffff", "curve": "stepped" },
					{ "time": 4.3333, "color": "ffffffff" },
					{ "time": 4.6666, "color": "ffffff00" }
				]
			},
			"cargo0": {
				"attachment": [
					{ "time": 0, "name": "flightScene/cargoBlue" }
				],
				"color": [
					{ "time": 0, "color": "ffffff00", "curve": "stepped" },
					{ "time": 2.6666, "color": "ffffff00" },
					{ "time": 2.8666, "color": "ffffffff", "curve": "stepped" },
					{ "time": 4.3333, "color": "ffffffff" },
					{ "time": 4.6666, "color": "ffffff00" }
				]
			},
			"human1": {
				"attachment": [
					{ "time": 0, "name": "flightScene/human" }
				],
				"color": [
					{ "time": 0, "color": "ffffff00" },
					{ "time": 0.3333, "color": "ffffffff", "curve": "stepped" },
					{ "time": 1.6666, "color": "ffffffff" },
					{ "time": 1.8666, "color": "ffffff00", "curve": "stepped" },
					{ "time": 2.6666, "color": "ffffff00" },
					{ "time": 2.8666, "color": "ffffffff", "curve": "stepped" },
					{ "time": 4.3333, "color": "ffffffff" },
					{ "time": 4.6666, "color": "ffffff00" }
				]
			},
			"human2": {
				"attachment": [
					{ "time": 0, "name": "flightScene/human" }
				],
				"color": [
					{ "time": 0, "color": "ffffff00" },
					{ "time": 0.3333, "color": "ffffffff", "curve": "stepped" },
					{ "time": 1.6666, "color": "ffffffff" },
					{ "time": 1.8666, "color": "ffffff00", "curve": "stepped" },
					{ "time": 2.6666, "color": "ffffff00" },
					{ "time": 2.8666, "color": "ffffffff", "curve": "stepped" },
					{ "time": 4.3333, "color": "ffffffff" },
					{ "time": 4.6666, "color": "ffffff00" }
				]
			},
			"human4": {
				"attachment": [
					{ "time": 0, "name": "flightScene/human" }
				],
				"color": [
					{ "time": 0, "color": "ffffff00" },
					{ "time": 0.3333, "color": "ffffffff", "curve": "stepped" },
					{ "time": 1.6666, "color": "ffffffff" },
					{ "time": 1.8666, "color": "ffffff00", "curve": "stepped" },
					{ "time": 2.6666, "color": "ffffff00" },
					{ "time": 2.8666, "color": "ffffffff", "curve": "stepped" },
					{ "time": 4.3333, "color": "ffffffff" },
					{ "time": 4.6666, "color": "ffffff00" }
				]
			},
			"cargo2": {
				"attachment": [
					{ "time": 0, "name": "flightScene/cargoBlue" }
				],
				"color": [
					{ "time": 0, "color": "ffffff00", "curve": "stepped" },
					{ "time": 2.6666, "color": "ffffff00" },
					{ "time": 2.8666, "color": "ffffffff", "curve": "stepped" },
					{ "time": 4.3333, "color": "ffffffff" },
					{ "time": 4.6666, "color": "ffffff00" }
				]
			},
			"cargo4": {
				"attachment": [
					{ "time": 0, "name": "flightScene/cargoBlue" }
				],
				"color": [
					{ "time": 0, "color": "ffffff00", "curve": "stepped" },
					{ "time": 2.6666, "color": "ffffff00" },
					{ "time": 2.8666, "color": "ffffffff", "curve": "stepped" },
					{ "time": 4.3333, "color": "ffffffff" },
					{ "time": 4.6666, "color": "ffffff00" }
				]
			}
		}
	},
	"planetin": {
		"bones": {
			"station": {
				"scale": [
					{
						"time": 0,
						"x": 0.1,
						"y": 0.1,
						"curve": [ 0, 0.99, 0.75, 1 ]
					},
					{ "time": 1, "x": 1, "y": 1 }
				]
			}
		},
		"slots": {
			"abandonedstation": {
				"color": [
					{ "time": 0, "color": "ffffff00" },
					{ "time": 1, "color": "ffffffff" }
				]
			}
		}
	},
	"planetout": {
		"bones": {
			"station": {
				"scale": [
					{
						"time": 0,
						"x": 1,
						"y": 1,
						"curve": [ 0.25, 0, 1, 0 ]
					},
					{ "time": 1, "x": 0.1, "y": 0.1 }
				]
			}
		},
		"slots": {
			"abandonedstation": {
				"color": [
					{ "time": 0, "color": "ffffffff" },
					{ "time": 1, "color": "ffffff00" }
				]
			}
		}
	}
}
}